{
  "saved_at": "2026-03-28T13:58:16.335890",
  "nodes": [
    {
      "id": "chunk_0_e0",
      "label": "Репозиторий",
      "archetype": "ASCO",
      "weight": 1.0,
      "embedding": [
        0.0034880751589856317,
        -0.5714201358929281,
        -0.15884845155315047,
        0.5708879116316823,
        0.505692091897455,
        -0.25806303805882724
      ],
      "metadata": {
        "type": "concept",
        "chunk": "chunk_0"
      }
    },
    {
      "id": "chunk_0_e1",
      "label": "Автор",
      "archetype": "ASCO",
      "weight": 1.0,
      "embedding": [
        -0.21463677767665404,
        0.2087513205640003,
        0.6308866476430589,
        -0.12797406963816313,
        0.42803135783400836,
        -0.5592385643605893
      ],
      "metadata": {
        "type": "concept",
        "chunk": "chunk_0"
      }
    },
    {
      "id": "chunk_0_e2",
      "label": "Дрезден",
      "archetype": "ASCO",
      "weight": 1.0,
      "embedding": [
        -0.39107940914788397,
        0.5876832085517135,
        -0.4278500582320863,
        0.5596847257930805,
        -0.008573901069848565,
        0.07286402220626123
      ],
      "metadata": {
        "type": "concept",
        "chunk": "chunk_0"
      }
    },
    {
      "id": "chunk_0_e3",
      "label": "Германия",
      "archetype": "ASCO",
      "weight": 1.0,
      "embedding": [
        -0.28462784060176005,
        0.07727731532836617,
        -0.5430685183979923,
        -0.33543382109774117,
        0.29517181946416765,
        -0.6468767594163591
      ],
      "metadata": {
        "type": "concept",
        "chunk": "chunk_0"
      }
    },
    {
      "id": "chunk_0_e4",
      "label": "Архив",
      "archetype": "ASCO",
      "weight": 1.0,
      "embedding": [
        -0.3112561527700268,
        0.6027227232998941,
        -0.5335647938726107,
        -0.4650294498264209,
        -0.052568580898613264,
        0.19009916364066895
      ],
      "metadata": {
        "type": "concept",
        "chunk": "chunk_0"
      }
    },
    {
      "id": "chunk_0_e5",
      "label": "Теги",
      "archetype": "ASCO",
      "weight": 1.0,
      "embedding": [
        0.12158866695009181,
        -0.2185457686863389,
        -0.6421497469877305,
        -0.1701172169523532,
        0.43776625660523305,
        -0.5518319332699204
      ],
      "metadata": {
        "type": "concept",
        "chunk": "chunk_0"
      }
    },
    {
      "id": "chunk_0_e6",
      "label": "Архитектуры",
      "archetype": "ASCO",
      "weight": 1.0,
      "embedding": [
        -0.5130459391430521,
        -0.10569695738267616,
        -0.6569864472569545,
        0.05823251691568153,
        -0.36001918753743567,
        0.4012181254979676
      ],
      "metadata": {
        "type": "concept",
        "chunk": "chunk_0"
      }
    },
    {
      "id": "chunk_0_e7",
      "label": "Колмогорова",
      "archetype": "ASCO",
      "weight": 1.0,
      "embedding": [
        -0.6583743030931306,
        0.6171332667072076,
        -0.23247964987926498,
        0.2877182609524958,
        0.057824619103923995,
        0.21334839179590048
      ],
      "metadata": {
        "type": "concept",
        "chunk": "chunk_0"
      }
    },
    {
      "id": "chunk_0_e8",
      "label": "Трансформер",
      "archetype": "ASCO",
      "weight": 1.0,
      "embedding": [
        0.37234296170285464,
        0.24822864113523635,
        0.2896000813244424,
        0.3309715215136485,
        0.2896000813244424,
        0.0
      ],
      "metadata": {
        "type": "concept",
        "chunk": "chunk_0"
      }
    },
    {
      "id": "chunk_1_e0",
      "label": "Инфраструктура",
      "archetype": "MSCO",
      "weight": 1.0,
      "embedding": [
        0.23017413505937437,
        0.11508706752968718,
        0.0,
        0.5178918038835923,
        0.23017413505937437,
        0.34526120258906157
      ],
      "metadata": {
        "type": "concept",
        "chunk": "chunk_1"
      }
    },
    {
      "id": "chunk_1_e1",
      "label": "Личная",
      "archetype": "ASCO",
      "weight": 1.0,
      "embedding": [
        0.0398827638847544,
        -0.5460095984990003,
        0.5873355925220226,
        0.28247305754763635,
        -0.4273413214434699,
        0.30480838570373425
      ],
      "metadata": {
        "type": "concept",
        "chunk": "chunk_1"
      }
    },
    {
      "id": "chunk_1_e2",
      "label": "Graphrag",
      "archetype": "ASCO",
      "weight": 1.0,
      "embedding": [
        0.40699406848152114,
        0.2713293789876807,
        0.2713293789876807,
        0.40699406848152114,
        0.3165509421522941,
        0.0
      ],
      "metadata": {
        "type": "concept",
        "chunk": "chunk_1"
      }
    },
    {
      "id": "chunk_1_e3",
      "label": "Структура",
      "archetype": "MSEO",
      "weight": 1.0,
      "embedding": [
        0.3409971697352368,
        0.4091966036822841,
        0.0,
        0.4091966036822841,
        0.4091966036822841,
        0.5455954715763789
      ],
      "metadata": {
        "type": "concept",
        "chunk": "chunk_1"
      }
    },
    {
      "id": "chunk_1_e4",
      "label": "Вектор",
      "archetype": "ASCO",
      "weight": 1.0,
      "embedding": [
        0.3859224924939799,
        0.3859224924939799,
        0.0,
        0.0,
        0.3859224924939799,
        0.49618606177797425
      ],
      "metadata": {
        "type": "concept",
        "chunk": "chunk_1"
      }
    },
    {
      "id": "chunk_1_e5",
      "label": "RISC",
      "archetype": "ASCO",
      "weight": 1.0,
      "embedding": [
        0.34606892612020956,
        0.5681927928948924,
        0.3696740700189364,
        0.4941011992749175,
        0.40780156522229355,
        0.10147028485855725
      ],
      "metadata": {
        "type": "concept",
        "chunk": "chunk_1"
      }
    },
    {
      "id": "chunk_1_e6",
      "label": "VAST",
      "archetype": "ASCO",
      "weight": 1.0,
      "embedding": [
        0.561838229858941,
        0.11292998432911093,
        -0.5139754331999831,
        -0.4199478132909258,
        -0.28077482921931723,
        0.3901579238773976
      ],
      "metadata": {
        "type": "concept",
        "chunk": "chunk_1"
      }
    },
    {
      "id": "chunk_2_e0",
      "label": "Тамагочи",
      "archetype": "ASCO",
      "weight": 1.0,
      "embedding": [
        -0.6496824452099395,
        -0.06166381298794414,
        0.4871471487767878,
        -0.5346309526756287,
        -0.11308096293417959,
        -0.19539803032655353
      ],
      "metadata": {
        "type": "concept",
        "chunk": "chunk_2"
      }
    },
    {
      "id": "chunk_2_e1",
      "label": "Бизнес",
      "archetype": "ASCO",
      "weight": 1.0,
      "embedding": [
        0.3731816021385014,
        -0.18104365075511158,
        0.19283133855662374,
        -0.3803780377310539,
        -0.6511871364812027,
        0.4712139905715318
      ],
      "metadata": {
        "type": "concept",
        "chunk": "chunk_2"
      }
    },
    {
      "id": "chunk_3_e0",
      "label": "Интернет",
      "archetype": "ASCO",
      "weight": 1.0,
      "embedding": [
        0.0801155527304174,
        0.43359899281039743,
        0.5730833303752481,
        0.2512247942107328,
        0.11385361742835387,
        -0.6333027432932657
      ],
      "metadata": {
        "type": "concept",
        "chunk": "chunk_3"
      }
    },
    {
      "id": "chunk_3_e1",
      "label": "Компьютер",
      "archetype": "ASCO",
      "weight": 1.0,
      "embedding": [
        -0.5545993167202111,
        0.31875496652119906,
        -0.5978809362312452,
        0.1154640671010032,
        0.46239763975615494,
        -0.07880182268974566
      ],
      "metadata": {
        "type": "concept",
        "chunk": "chunk_3"
      }
    },
    {
      "id": "chunk_3_e2",
      "label": "Дроны",
      "archetype": "ASCO",
      "weight": 1.0,
      "embedding": [
        0.6531652710429414,
        -0.1578346861135722,
        0.5334669969301448,
        -0.30073502272168645,
        0.2924792651324263,
        0.29646353793569075
      ],
      "metadata": {
        "type": "concept",
        "chunk": "chunk_3"
      }
    },
    {
      "id": "chunk_3_e3",
      "label": "Баба",
      "archetype": "ASCO",
      "weight": 1.0,
      "embedding": [
        0.5174635307109867,
        -0.22387328674109477,
        0.12180737358738453,
        -0.4779012882365277,
        -0.6292216332286569,
        0.2072817034533723
      ],
      "metadata": {
        "type": "concept",
        "chunk": "chunk_3"
      }
    },
    {
      "id": "chunk_3_e4",
      "label": "Нейрон",
      "archetype": "ASCO",
      "weight": 1.0,
      "embedding": [
        -0.06234796863885497,
        0.3740878118331298,
        0.4987837491108398,
        0.3117398431942749,
        0.0,
        0.0
      ],
      "metadata": {
        "type": "concept",
        "chunk": "chunk_3"
      }
    },
    {
      "id": "chunk_3_e5",
      "label": "Токен",
      "archetype": "ASCO",
      "weight": 1.0,
      "embedding": [
        0.4626519455729922,
        0.2313259727864961,
        0.0,
        0.0,
        0.5204834387696162,
        0.4626519455729922
      ],
      "metadata": {
        "type": "concept",
        "chunk": "chunk_3"
      }
    },
    {
      "id": "chunk_3_e6",
      "label": "IPFS",
      "archetype": "ASCO",
      "weight": 1.0,
      "embedding": [
        0.285354627981812,
        0.29333560224654015,
        0.20715381210009634,
        -0.42919126891418924,
        0.4620305195260153,
        -0.6260486503385883
      ],
      "metadata": {
        "type": "concept",
        "chunk": "chunk_3"
      }
    },
    {
      "id": "chunk_3_e7",
      "label": "WILOS",
      "archetype": "ASCO",
      "weight": 1.0,
      "embedding": [
        -0.15111145802426967,
        -0.6837927453008437,
        0.19323595535386845,
        -0.04901924695742254,
        0.078975872971624,
        0.6808910332808694
      ],
      "metadata": {
        "type": "concept",
        "chunk": "chunk_3"
      }
    },
    {
      "id": "chunk_4_e0",
      "label": "Формализмы",
      "archetype": "ASCO",
      "weight": 1.0,
      "embedding": [
        -0.7855864408310584,
        0.013332656574261938,
        0.5069474054303944,
        -0.32054543614680175,
        -0.08001295219937322,
        0.1285654044611211
      ],
      "metadata": {
        "type": "concept",
        "chunk": "chunk_4"
      }
    },
    {
      "id": "chunk_4_e1",
      "label": "Сефирот",
      "archetype": "ASCO",
      "weight": 1.0,
      "embedding": [
        -0.37487744250892135,
        0.3533142460266666,
        -0.535939525082312,
        -0.5123419902359347,
        0.2582947115808517,
        0.3437939777214987
      ],
      "metadata": {
        "type": "concept",
        "chunk": "chunk_4"
      }
    },
    {
      "id": "chunk_4_e2",
      "label": "Милогия",
      "archetype": "ASCO",
      "weight": 1.0,
      "embedding": [
        0.79424245136971,
        0.554433413080717,
        0.1728067340135056,
        0.055269351882285565,
        -0.16321344209836558,
        -0.04719134075656426
      ],
      "metadata": {
        "type": "concept",
        "chunk": "chunk_4"
      }
    },
    {
      "id": "chunk_4_e3",
      "label": "Блокчейн",
      "archetype": "ASCO",
      "weight": 1.0,
      "embedding": [
        -0.4066424839941569,
        0.5403661985976604,
        -0.331713433044405,
        0.07139061907296411,
        -0.2718801427780537,
        -0.5946402504316662
      ],
      "metadata": {
        "type": "concept",
        "chunk": "chunk_4"
      }
    },
    {
      "id": "chunk_4_e4",
      "label": "Образ",
      "archetype": "ASEF",
      "weight": 1.0,
      "embedding": [
        -0.7524733269853034,
        0.4938323173846297,
        0.09565286062015521,
        -0.10457911151123314,
        -0.1876295085251332,
        -0.3669093099166523
      ],
      "metadata": {
        "type": "concept",
        "chunk": "chunk_4"
      }
    },
    {
      "id": "chunk_4_e5",
      "label": "Цифровой",
      "archetype": "ASCO",
      "weight": 1.0,
      "embedding": [
        0.45387303085670677,
        0.8091060124809477,
        -0.1123941316534481,
        -0.20391571461359947,
        0.2586563902400066,
        -0.13501683124569816
      ],
      "metadata": {
        "type": "concept",
        "chunk": "chunk_4"
      }
    },
    {
      "id": "chunk_4_e7",
      "label": "Модель",
      "archetype": "ASCO",
      "weight": 1.0,
      "embedding": [
        0.5091750772173156,
        0.4364357804719848,
        0.2909571869813232,
        0.3636964837266541,
        0.4364357804719848,
        0.0
      ],
      "metadata": {
        "type": "concept",
        "chunk": "chunk_4"
      }
    },
    {
      "id": "chunk_4_e8",
      "label": "Архитектура",
      "archetype": "MSCO",
      "weight": 1.0,
      "embedding": [
        0.46770717334674267,
        0.3340765523905305,
        0.0,
        0.46770717334674267,
        0.4008918628686366,
        0.46770717334674267
      ],
      "metadata": {
        "type": "concept",
        "chunk": "chunk_4"
      }
    },
    {
      "id": "chunk_5_e0",
      "label": "Супер",
      "archetype": "ASCO",
      "weight": 1.0,
      "embedding": [
        0.5721075552237724,
        0.1761375979525222,
        0.7046993849667875,
        0.008665289812202744,
        -0.131653870678905,
        0.3572946119920619
      ],
      "metadata": {
        "type": "concept",
        "chunk": "chunk_5"
      }
    },
    {
      "id": "chunk_5_e1",
      "label": "Нейро",
      "archetype": "ASCO",
      "weight": 1.0,
      "embedding": [
        0.41905817746174695,
        0.23281009858985943,
        0.3724961577437751,
        0.3259341380258032,
        0.2793721183078313,
        0.0
      ],
      "metadata": {
        "type": "concept",
        "chunk": "chunk_5"
      }
    },
    {
      "id": "chunk_5_e3",
      "label": "Караван",
      "archetype": "ASCO",
      "weight": 1.0,
      "embedding": [
        0.5291181678430921,
        -0.452235196289234,
        0.4028402180381171,
        0.005413108130472042,
        0.5331046154219765,
        -0.26269224903442434
      ],
      "metadata": {
        "type": "concept",
        "chunk": "chunk_5"
      }
    },
    {
      "id": "chunk_5_e4",
      "label": "Портал",
      "archetype": "ASCO",
      "weight": 1.0,
      "embedding": [
        -0.34767380492312555,
        -0.4155614211323366,
        0.02279411050880365,
        0.36332827595359524,
        0.39485090843176474,
        0.6465271712511856
      ],
      "metadata": {
        "type": "concept",
        "chunk": "chunk_5"
      }
    },
    {
      "id": "chunk_5_e5",
      "label": "NATS",
      "archetype": "ASCO",
      "weight": 1.0,
      "embedding": [
        0.42895703688056197,
        -0.22648601961682843,
        -0.06071648163651076,
        0.4861923267655723,
        -0.26589945429613815,
        0.6737417560799923
      ],
      "metadata": {
        "type": "concept",
        "chunk": "chunk_5"
      }
    },
    {
      "id": "chunk_5_e6",
      "label": "MQTT",
      "archetype": "ASCO",
      "weight": 1.0,
      "embedding": [
        -0.5600235671062308,
        0.5513804590626292,
        0.28178083268346904,
        -0.07018825332734638,
        -0.4566939992364997,
        0.2990935574998843
      ],
      "metadata": {
        "type": "concept",
        "chunk": "chunk_5"
      }
    },
    {
      "id": "chunk_6_e0",
      "label": "Социальное",
      "archetype": "ASCO",
      "weight": 1.0,
      "embedding": [
        -0.3978142238299944,
        -0.5131829811870114,
        0.0629980338316807,
        -0.13594732058782685,
        -0.5077756870486202,
        0.5459858025069748
      ],
      "metadata": {
        "type": "concept",
        "chunk": "chunk_6"
      }
    },
    {
      "id": "chunk_6_e1",
      "label": "Германии",
      "archetype": "ASCO",
      "weight": 1.0,
      "embedding": [
        0.4834296140791604,
        0.23491341061119428,
        -0.14255793679361717,
        0.4408215029823176,
        0.5136000372791336,
        -0.4823692948548038
      ],
      "metadata": {
        "type": "concept",
        "chunk": "chunk_6"
      }
    },
    {
      "id": "chunk_6_e2",
      "label": "Мастер",
      "archetype": "ASCO",
      "weight": 1.0,
      "embedding": [
        -0.4125604819385658,
        0.32045383008154826,
        0.34919673823842834,
        -0.2705316704369648,
        -0.507010302531849,
        -0.5243262323682419
      ],
      "metadata": {
        "type": "concept",
        "chunk": "chunk_6"
      }
    },
    {
      "id": "chunk_7_e1",
      "label": "Изобретения",
      "archetype": "ASCO",
      "weight": 1.0,
      "embedding": [
        -0.29880371377925435,
        -0.31385496149147635,
        0.23510749319675667,
        -0.6801832320952131,
        -0.22938811198685485,
        -0.49159712700265246
      ],
      "metadata": {
        "type": "concept",
        "chunk": "chunk_7"
      }
    },
    {
      "id": "chunk_7_e2",
      "label": "Пыле",
      "archetype": "ASCO",
      "weight": 1.0,
      "embedding": [
        -0.527091776265602,
        -0.5479547278869779,
        0.49086152246921855,
        -0.26822827677239097,
        0.22477090601192784,
        0.24188111271649967
      ],
      "metadata": {
        "type": "concept",
        "chunk": "chunk_7"
      }
    },
    {
      "id": "chunk_7_e3",
      "label": "Спираль",
      "archetype": "ASCO",
      "weight": 1.0,
      "embedding": [
        -0.49077151736106833,
        -0.5690718425113422,
        -0.38482648290665983,
        0.4497056720830659,
        -0.1910572217707436,
        -0.22016148702058155
      ],
      "metadata": {
        "type": "concept",
        "chunk": "chunk_7"
      }
    }
  ],
  "edges": [
    {
      "source": "chunk_0_e0",
      "target": "chunk_0_e1",
      "label": "связан",
      "weight": 0.7,
      "directed": true
    },
    {
      "source": "chunk_1_e0",
      "target": "chunk_1_e1",
      "label": "связан",
      "weight": 0.7,
      "directed": true
    },
    {
      "source": "chunk_2_e0",
      "target": "chunk_2_e1",
      "label": "связан",
      "weight": 0.7,
      "directed": true
    },
    {
      "source": "chunk_3_e0",
      "target": "chunk_3_e1",
      "label": "связан",
      "weight": 0.7,
      "directed": true
    },
    {
      "source": "chunk_4_e0",
      "target": "chunk_4_e1",
      "label": "связан",
      "weight": 0.7,
      "directed": true
    },
    {
      "source": "chunk_5_e0",
      "target": "chunk_5_e1",
      "label": "связан",
      "weight": 0.7,
      "directed": true
    },
    {
      "source": "chunk_6_e0",
      "target": "chunk_6_e1",
      "label": "связан",
      "weight": 0.7,
      "directed": true
    },
    {
      "source": "chunk_6_e2",
      "target": "chunk_7_e1",
      "label": "связан",
      "weight": 0.7,
      "directed": true
    }
  ]
}